{
    "members": [
        {
            "id": 10, 
            "issues": {
                "new": 4, 
                "open": 2, 
                "closed": 3
            }, 
            "name": "Ha\u00efkel Gu\u00e9mar"
        }, 
        {
            "id": 13, 
            "issues": {
                "new": 2, 
                "open": 0, 
                "closed": 1
            }, 
            "name": "Benjamin Depardon"
        }, 
        {
            "id": 17, 
            "issues": {
                "new": 1, 
                "open": 1, 
                "closed": 0
            }, 
            "name": "Philippe Martinez"
        }, 
        {
            "id": 19, 
            "issues": {
                "new": 1, 
                "open": 0, 
                "closed": 0
            }, 
            "name": "Olivier Mornard"
        }, 
        {
            "id": 20, 
            "issues": {
                "new": 0, 
                "open": 1, 
                "closed": 1
            }, 
            "name": "Augustin Ragon"
        }, 
        {
            "id": 22, 
            "issues": {
                "new": 0, 
                "open": 0, 
                "closed": 0
            }, 
            "name": "Nicolas Bard"
        }, 
        {
            "id": 23, 
            "issues": {
                "new": 0, 
                "open": 5, 
                "closed": 1
            }, 
            "name": "Rodrigue Chakode"
        }, 
        {
            "id": 25, 
            "issues": {
                "new": 0, 
                "open": 0, 
                "closed": 0
            }, 
            "name": "sysfera sysfera"
        }, 
        {
            "id": 29, 
            "issues": {
                "new": 1, 
                "open": 3, 
                "closed": 0
            }, 
            "name": "K\u00e9vin Coulomb"
        }, 
        {
            "id": 32, 
            "issues": {
                "new": 0, 
                "open": 0, 
                "closed": 0
            }, 
            "name": "Amine Bsila"
        }
    ]
}